jenkins_badges/__init__.py
jenkins_badges/__version__.py
jenkins_badges/coverage_badge/__init__.py
jenkins_badges/coverage_badge/static/error_badge.svg
jenkins_badges-1.2.0.dist-info/DESCRIPTION.rst
jenkins_badges-1.2.0.dist-info/METADATA
jenkins_badges-1.2.0.dist-info/RECORD
jenkins_badges-1.2.0.dist-info/WHEEL
jenkins_badges-1.2.0.dist-info/metadata.json
jenkins_badges-1.2.0.dist-info/top_level.txt
