Metadata-Version: 2.0
Name: jenkins-badges
Version: 1.2.0
Summary: provides badge images based on jenkins data
Home-page: https://github.com/jeremyarr/jenkins_badges
Author: Jeremy Arr
Author-email: jeremyarr@gmail.com
License: MIT
Keywords: jenkins,coverage,cobertura,badges,shields,github
Platform: UNKNOWN
Classifier: Development Status :: 4 - Beta
Classifier: Intended Audience :: Developers
Classifier: Framework :: Flask
Classifier: License :: OSI Approved :: MIT License
Classifier: Programming Language :: Python :: 2.7
Classifier: Programming Language :: Python :: 3
Classifier: Topic :: Software Development :: Testing
Requires-Dist: flask
Requires-Dist: requests
Requires-Dist: six
